modis_news_utils/__init__.py
modis_news_utils/custom_types.py
modis_news_utils/news_utils.py
modis_news_utils-0.0.6.dist-info/METADATA
modis_news_utils-0.0.6.dist-info/WHEEL
modis_news_utils-0.0.6.dist-info/RECORD
